{
  "artifactsLocation": {
    "internalSchema": "${task.onboarding_storage-umkx.internalSchema}",
    "taskSchema": "${task.onboarding_storage-umkx.taskSchema}",
    "databaseName": "${task.onboarding_storage-umkx.databaseName}"
  },
  "artifactsSettings": {
    "liveViewsEnabled": true,
    "historyEnabled": true,
    "artifactsPrefix": ""
  },
  "taskRuntime": {
    "tableUpdateConcurrency": 10,
    "warehouseSelection": {
      "warehouseName": "${task.onboarding_storage-umkx.warehouseName}",
      "selectionMethod": "${task.onboarding_storage-umkx.warehouseSelectionMethod}"
    }
  }
}