{
  "projectName": "",
  "platformConnection": "",
  "platformType": "",
  "project.current.prefixSchema": "",
  "task-type.landing.warehouseName": "",
  "task-type.landing.warehouseSelectionMethod": "",
  "task-type.landing.databaseName": "",
  "task-type.landing.databaseSelectionMethod": "",
  "task-type.registered.databaseName": "",
  "task-type.registered.databaseSelectionMethod": "",
  "task-type.storage.warehouseName": "",
  "task-type.storage.warehouseSelectionMethod": "",
  "task-type.storage.databaseName": "",
  "task-type.storage.databaseSelectionMethod": "",
  "task-type.transform.warehouseName": "",
  "task-type.transform.warehouseSelectionMethod": "",
  "task-type.transform.databaseName": "",
  "task-type.transform.databaseSelectionMethod": "",
  "task-type.datamart.warehouseName": "",
  "task-type.datamart.warehouseSelectionMethod": "",
  "task-type.datamart.databaseName": "",
  "task-type.datamart.databaseSelectionMethod": "",
  "task.land1-sl1z.databaseName": "",
  "task.land1-sl1z.taskSchema": "",
  "task.land1-sl1z.sourceConnection": "",
  "task.land1-sl1z:null$_$dbo.database": "",
  "task.land1-sl1z:null$_$dbo.schema": "",
  "task.land1-sl1z:AutoNorthwind$_$dbo.database": "",
  "task.land1-sl1z:AutoNorthwind$_$dbo.schema": "",
  "task.store1-ln5f.databaseName": "",
  "task.store1-ln5f.internalSchema": "",
  "task.store1-ln5f.taskSchema": "",
  "task.store1-ln5f.warehouseName": "",
  "task.store1-ln5f.warehouseSelectionMethod": "",
  "task.store1-ln5f:null$_$null.schema": ""
}