{
  "projectName": "",
  "platformConnection": "",
  "platformType": "",
  "project.current.prefixSchema": "",
  "task-type.landing.warehouseName": "",
  "task-type.landing.warehouseSelectionMethod": "",
  "task-type.landing.databaseName": "",
  "task-type.landing.databaseSelectionMethod": "",
  "task-type.registered.databaseName": "",
  "task-type.registered.databaseSelectionMethod": "",
  "task-type.storage.warehouseName": "",
  "task-type.storage.warehouseSelectionMethod": "",
  "task-type.storage.databaseName": "",
  "task-type.storage.databaseSelectionMethod": "",
  "task-type.transform.warehouseName": "",
  "task-type.transform.warehouseSelectionMethod": "",
  "task-type.transform.databaseName": "",
  "task-type.transform.databaseSelectionMethod": "",
  "task-type.datamart.warehouseName": "",
  "task-type.datamart.warehouseSelectionMethod": "",
  "task-type.datamart.databaseName": "",
  "task-type.datamart.databaseSelectionMethod": "",
  "task.landing-mbs2.databaseName": "",
  "task.landing-mbs2.taskSchema": "",
  "task.landing-mbs2.sourceConnection": "",
  "task.landing-mbs2:null$_$dbo.database": "",
  "task.landing-mbs2:null$_$dbo.schema": "",
  "task.landing-mbs2:AutoNorthwind$_$dbo.database": "",
  "task.landing-mbs2:AutoNorthwind$_$dbo.schema": "",
  "task.storage-hjn4.databaseName": "",
  "task.storage-hjn4.internalSchema": "",
  "task.storage-hjn4.taskSchema": "",
  "task.storage-hjn4.warehouseName": "",
  "task.storage-hjn4:null$_$%.schemaPattern": "",
  "task.transform-mbs9.databaseName": "",
  "task.transform-mbs9.internalSchema": "",
  "task.transform-mbs9.taskSchema": "",
  "task.transform-mbs9.warehouseName": "",
  "task.transform-mbs9:null$_$%.schemaPattern": ""
}