{
  "id": "order_details-l-pw",
  "name": "Order Details",
  "type": "STORAGE",
  "inputDatasets": [
    {
      "datasetId": "order_details",
      "name": "Order Details",
      "projectId": "{{ref(project.current.projectId)}}",
      "taskId": "landing-l-pt"
    }
  ],
  "datasetAttributes": {
    "materialized": "INHERIT",
    "hasHistory": "INHERIT",
    "hasLiveViews": "INHERIT",
    "hasChanges": "INHERIT",
    "hasStandardViewsWithHeaders": "INHERIT",
    "watermarkIncrementalSettings": "INHERIT"
  }
}