{
  "sourceConnection": "${task.landing-pizh.sourceConnection}",
  "includePatterns": [],
  "excludePatterns": [],
  "explicitlySelected": [
    {
      "database": "${task.landing-pizh:null$_$dbo.database}",
      "sourceProject": "${ref(project.current.projectId)}",
      "sourceTask": "landing-pizh",
      "name": "Categories",
      "schema": "${task.landing-pizh:null$_$dbo.schema}",
      "type": "TABLE",
      "sourceTableId": "$replicate$dbo_categories"
    },
    {
      "database": "${task.landing-pizh:null$_$dbo.database}",
      "sourceProject": "${ref(project.current.projectId)}",
      "sourceTask": "landing-pizh",
      "name": "Order Details",
      "schema": "${task.landing-pizh:null$_$dbo.schema}",
      "type": "TABLE",
      "sourceTableId": "$replicate$dbo_order_details"
    },
    {
      "database": "${task.landing-pizh:null$_$dbo.database}",
      "sourceProject": "${ref(project.current.projectId)}",
      "sourceTask": "landing-pizh",
      "name": "Products",
      "schema": "${task.landing-pizh:null$_$dbo.schema}",
      "type": "TABLE",
      "sourceTableId": "$replicate$dbo_products"
    },
    {
      "database": "${task.landing-pizh:null$_$dbo.database}",
      "sourceProject": "${ref(project.current.projectId)}",
      "sourceTask": "landing-pizh",
      "name": "Suppliers",
      "schema": "${task.landing-pizh:null$_$dbo.schema}",
      "type": "TABLE",
      "sourceTableId": "$replicate$dbo_suppliers"
    }
  ]
}