{
  "projectName": "",
  "platformConnection": "",
  "platformType": "",
  "project.current.prefixSchema": "",
  "task-type.landing.warehouseName": "",
  "task-type.landing.warehouseSelectionMethod": "",
  "task-type.landing.databaseName": "",
  "task-type.landing.databaseSelectionMethod": "",
  "task-type.registered.databaseName": "",
  "task-type.registered.databaseSelectionMethod": "",
  "task-type.storage.warehouseName": "",
  "task-type.storage.warehouseSelectionMethod": "",
  "task-type.storage.databaseName": "",
  "task-type.storage.databaseSelectionMethod": "",
  "task-type.transform.warehouseName": "",
  "task-type.transform.warehouseSelectionMethod": "",
  "task-type.transform.databaseName": "",
  "task-type.transform.databaseSelectionMethod": "",
  "task-type.datamart.warehouseName": "",
  "task-type.datamart.warehouseSelectionMethod": "",
  "task-type.datamart.databaseName": "",
  "task-type.datamart.databaseSelectionMethod": "",
  "task.onboarding_landing-g7n7.databaseName": "",
  "task.onboarding_landing-g7n7.taskSchema": "",
  "task.onboarding_landing-g7n7.sourceConnection": "",
  "task.onboarding_landing-g7n7:null$_$dbo.database": "",
  "task.onboarding_landing-g7n7:null$_$dbo.schema": "",
  "task.onboarding_landing-g7n7:AutoNorthwind$_$dbo.database": "",
  "task.onboarding_landing-g7n7:AutoNorthwind$_$dbo.schema": "",
  "task.onboarding_storage-g7n8.databaseName": "",
  "task.onboarding_storage-g7n8.internalSchema": "",
  "task.onboarding_storage-g7n8.taskSchema": "",
  "task.onboarding_storage-g7n8.warehouseName": "",
  "task.onboarding_storage-g7n8:null$_$%.schemaPattern": ""
}