{
  "id": "shipping_zones_price_based_shipping_rates-qjv_",
  "name": "shipping_zones_price_based_shipping_rates",
  "type": "STORAGE",
  "inputDatasets": [
    {
      "datasetId": "shipping_zones_price_based_shipping_rates",
      "name": "shipping_zones_price_based_shipping_rates",
      "projectId": "{{ref(project.current.projectId)}}",
      "taskId": "shopify_landing-qjv4"
    }
  ],
  "datasetAttributes": {
    "materialized": "INHERIT",
    "hasHistory": "INHERIT",
    "hasLiveViews": "INHERIT",
    "hasChanges": "INHERIT",
    "hasStandardViewsWithHeaders": "INHERIT",
    "watermarkIncrementalSettings": "INHERIT"
  }
}