{
  "id": "categories-nyxc",
  "name": "Categories",
  "type": "STORAGE",
  "inputDatasets": [
    {
      "datasetId": "categories",
      "name": "Categories",
      "projectId": "{{ref(project.current.projectId)}}",
      "taskId": "landing_1-8isl"
    }
  ],
  "datasetAttributes": {
    "materialized": "INHERIT",
    "hasHistory": "INHERIT",
    "hasLiveViews": "INHERIT",
    "hasChanges": "INHERIT",
    "hasStandardViewsWithHeaders": "INHERIT",
    "watermarkIncrementalSettings": "INHERIT"
  }
}