{
  "artifactsSettings": {
    "liveViewsEnabled": false,
    "historyEnabled": false,
    "artifactsPrefix": ""
  },
  "artifactsLocation": {
    "internalSchema": "{{task.data_mart-vegl.internalSchema}}",
    "taskSchema": "{{task.data_mart-vegl.taskSchema}}",
    "databaseName": "{{task.data_mart-vegl.databaseName}}"
  },
  "taskRuntime": {
    "tableUpdateConcurrency": 10,
    "warehouseSelection": {
      "warehouseName": "{{task.data_mart-vegl.warehouseName}}",
      "selectionMethod": "{{task.data_mart-vegl.warehouseSelectionMethod}}"
    }
  }
}